{"@module": "pymatgen.core.structure", "@class": "Structure", "charge": "null", "lattice": {"a": 8.17, "b": 8.17, "c": 8.17, "alpha": 90, "beta": 90, "gamma": 90}, "energy": -395.33091, "sites": [{"species": [{"element": "Mg", "oxidation_state": 2.0, "occu": 1}], "abc": [0.7497046864171607, 0.2459040715148951, 0.2515445634206306], "label": "Mg2+:1", "properties": {}}, {"species": [{"element": "Mg", "oxidation_state": 2.0, "occu": 1}], "abc": [0.2501749433905548, 0.7452094488331502, 0.2544985511389138], "label": "Mg2+:1", "properties": {}}, {"species": [{"element": "Mg", "oxidation_state": 2.0, "occu": 1}], "abc": [0.1231125796636615, 0.8772641266027175, 0.8753851936937557], "label": "Mg2+:1", "properties": {}}, {"species": [{"element": "Mg", "oxidation_state": 2.0, "occu": 1}], "abc": [0.3738244694038142, 0.6270250810147746, 0.8752132854845465], "label": "Mg2+:1", "properties": {}}, {"species": [{"element": "Mg", "oxidation_state": 2.0, "occu": 1}], "abc": [0.8773249743172469, 0.1232170606488208, 0.87524306779888], "label": "Mg2+:1", "properties": {}}, {"species": [{"element": "Mg", "oxidation_state": 2.0, "occu": 1}], "abc": [0.8767002438547892, 0.6250099104338438, 0.3758628990053047], "label": "Mg2+:1", "properties": {}}, {"species": [{"element": "Mg", "oxidation_state": 2.0, "occu": 1}], "abc": [0.1223830806717453, 0.1213947690511192, 0.1217075539194187], "label": "Mg2+:1", "properties": {}}, {"species": [{"element": "Mg", "oxidation_state": 2.0, "occu": 1}], "abc": [0.6272414036977157, 0.1232194814963407, 0.6272908945685319], "label": "Mg2+:1", "properties": {}}, {"species": [{"element": "Al", "oxidation_state": 3.0, "occu": 1}], "abc": [0.2512045517680626, 0.2471342662495485, 0.7507722027258369], "label": "Al3+:1", "properties": {}}, {"species": [{"element": "Al", "oxidation_state": 3.0, "occu": 1}], "abc": [0.7496416627148789, 0.7425270432817657, 0.7523682307248475], "label": "Al3+:1", "properties": {}}, {"species": [{"element": "Al", "oxidation_state": 3.0, "occu": 1}], "abc": [0.4983307491457512, 0.50581835042975, 0.4977740347122408], "label": "Al3+:1", "properties": {}}, {"species": [{"element": "Al", "oxidation_state": 3.0, "occu": 1}], "abc": [-0.0023108350805955, 0.5052792739494618, 0.9961594604421894], "label": "Al3+:1", "properties": {}}, {"species": [{"element": "Al", "oxidation_state": 3.0, "occu": 1}], "abc": [0.0015620928637358, 0.0049395186505255, 0.4957068145070263], "label": "Al3+:1", "properties": {}}, {"species": [{"element": "Al", "oxidation_state": 3.0, "occu": 1}], "abc": [0.5025721819242536, 0.0063921635711687, -0.0003514800472643], "label": "Al3+:1", "properties": {}}, {"species": [{"element": "Al", "oxidation_state": 3.0, "occu": 1}], "abc": [0.6237711137211291, 0.8781928458020134, 0.3777961984777947], "label": "Al3+:1", "properties": {}}, {"species": [{"element": "Al", "oxidation_state": 3.0, "occu": 1}], "abc": [0.6244813031366131, 0.3754891667260862, 0.8755837621108197], "label": "Al3+:1", "properties": {}}, {"species": [{"element": "Al", "oxidation_state": 3.0, "occu": 1}], "abc": [0.3764516897924909, 0.3775144844068204, 0.1204317427886863], "label": "Al3+:1", "properties": {}}, {"species": [{"element": "Al", "oxidation_state": 3.0, "occu": 1}], "abc": [0.3759505540421941, 0.8772716476014379, 0.6260845213692406], "label": "Al3+:1", "properties": {}}, {"species": [{"element": "Al", "oxidation_state": 3.0, "occu": 1}], "abc": [0.1221282567397318, 0.3767035189773132, 0.3773325863877227], "label": "Al3+:1", "properties": {}}, {"species": [{"element": "Al", "oxidation_state": 3.0, "occu": 1}], "abc": [0.3783036928937931, 0.1232024344791807, 0.3779188871091935], "label": "Al3+:1", "properties": {}}, {"species": [{"element": "Al", "oxidation_state": 3.0, "occu": 1}], "abc": [0.1236525686186786, 0.6243217028817317, 0.6254222640178669], "label": "Al3+:1", "properties": {}}, {"species": [{"element": "Al", "oxidation_state": 3.0, "occu": 1}], "abc": [0.8783165371398528, 0.8780841244724599, 0.1198311199427336], "label": "Al3+:1", "properties": {}}, {"species": [{"element": "Al", "oxidation_state": 3.0, "occu": 1}], "abc": [0.8775062967520355, 0.3741911841559891, 0.6246211596079052], "label": "Al3+:1", "properties": {}}, {"species": [{"element": "Al", "oxidation_state": 3.0, "occu": 1}], "abc": [0.6217554755914481, 0.6232722874069063, 0.1215798461057275], "label": "Al3+:1", "properties": {}}, {"species": [{"element": "O", "oxidation_state": -2.0, "occu": 1}], "abc": [0.1262098325226862, 0.1266081532686792, 0.8741223858295626], "label": "O2-:1", "properties": {}}, {"species": [{"element": "O", "oxidation_state": -2.0, "occu": 1}], "abc": [0.8934322031160926, 0.3775664070615557, 0.3961898183364755], "label": "O2-:1", "properties": {}}, {"species": [{"element": "O", "oxidation_state": -2.0, "occu": 1}], "abc": [0.3895446630160079, 0.8905199719386638, 0.3937102315673835], "label": "O2-:1", "properties": {}}, {"species": [{"element": "O", "oxidation_state": -2.0, "occu": 1}], "abc": [0.6249122701005865, 0.6129541627838918, 0.8822435480158773], "label": "O2-:1", "properties": {}}, {"species": [{"element": "O", "oxidation_state": -2.0, "occu": 1}], "abc": [0.3848889178905954, 0.3712623382021731, 0.8805784990417681], "label": "O2-:1", "properties": {}}, {"species": [{"element": "O", "oxidation_state": -2.0, "occu": 1}], "abc": [0.6055382824295897, 0.1071226462718622, 0.3837620546018614], "label": "O2-:1", "properties": {}}, {"species": [{"element": "O", "oxidation_state": -2.0, "occu": 1}], "abc": [0.8637532055772136, 0.3782327744018587, 0.8643553881038826], "label": "O2-:1", "properties": {}}, {"species": [{"element": "O", "oxidation_state": -2.0, "occu": 1}], "abc": [0.1406527427842525, 0.1387631019386418, 0.3775332164780259], "label": "O2-:1", "properties": {}}, {"species": [{"element": "O", "oxidation_state": -2.0, "occu": 1}], "abc": [0.621208456365984, 0.635417365173395, 0.3629819376666409], "label": "O2-:1", "properties": {}}, {"species": [{"element": "O", "oxidation_state": -2.0, "occu": 1}], "abc": [0.3815988869965686, 0.8798131821242009, 0.8610785307698665], "label": "O2-:1", "properties": {}}, {"species": [{"element": "O", "oxidation_state": -2.0, "occu": 1}], "abc": [0.1253210121933419, 0.6219067103118227, 0.8585897939237672], "label": "O2-:1", "properties": {}}, {"species": [{"element": "O", "oxidation_state": -2.0, "occu": 1}], "abc": [0.8613760602263298, 0.8784193965994705, 0.3689211646062796], "label": "O2-:1", "properties": {}}, {"species": [{"element": "O", "oxidation_state": -2.0, "occu": 1}], "abc": [0.6234734092506632, 0.1426491949929758, 0.8753340442744229], "label": "O2-:1", "properties": {}}, {"species": [{"element": "O", "oxidation_state": -2.0, "occu": 1}], "abc": [0.1224147210059083, 0.6027253713795974, 0.3990395946588453], "label": "O2-:1", "properties": {}}, {"species": [{"element": "O", "oxidation_state": -2.0, "occu": 1}], "abc": [0.8663263837014978, 0.8712909632270438, 0.8821586619622845], "label": "O2-:1", "properties": {}}, {"species": [{"element": "O", "oxidation_state": -2.0, "occu": 1}], "abc": [0.3707779846426241, 0.3659266788185336, 0.3691532839965503], "label": "O2-:1", "properties": {}}, {"species": [{"element": "O", "oxidation_state": -2.0, "occu": 1}], "abc": [0.3929614098519052, 0.6062220431379323, 0.1190586788603405], "label": "O2-:1", "properties": {}}, {"species": [{"element": "O", "oxidation_state": -2.0, "occu": 1}], "abc": [0.6119833702313041, 0.3906968821888989, 0.1085302806747575], "label": "O2-:1", "properties": {}}, {"species": [{"element": "O", "oxidation_state": -2.0, "occu": 1}], "abc": [0.3725178447509366, 0.117036383492092, 0.6159750040419641], "label": "O2-:1", "properties": {}}, {"species": [{"element": "O", "oxidation_state": -2.0, "occu": 1}], "abc": [0.6177235756289725, 0.8642744462882284, 0.6167523844876791], "label": "O2-:1", "properties": {}}, {"species": [{"element": "O", "oxidation_state": -2.0, "occu": 1}], "abc": [0.8850733118218701, 0.6145024619571698, 0.629059665729797], "label": "O2-:1", "properties": {}}, {"species": [{"element": "O", "oxidation_state": -2.0, "occu": 1}], "abc": [0.1227503773936077, 0.3820500690228782, 0.6225110646002227], "label": "O2-:1", "properties": {}}, {"species": [{"element": "O", "oxidation_state": -2.0, "occu": 1}], "abc": [0.8780497079178353, 0.1025610576605974, 0.1177381920080255], "label": "O2-:1", "properties": {}}, {"species": [{"element": "O", "oxidation_state": -2.0, "occu": 1}], "abc": [0.1038058565071005, 0.8726108513878362, 0.1201205553762827], "label": "O2-:1", "properties": {}}, {"species": [{"element": "O", "oxidation_state": -2.0, "occu": 1}], "abc": [0.1336925871189426, 0.8638012904595823, 0.6166385990225952], "label": "O2-:1", "properties": {}}, {"species": [{"element": "O", "oxidation_state": -2.0, "occu": 1}], "abc": [0.3649297099236891, 0.6359719844711491, 0.6220031413977526], "label": "O2-:1", "properties": {}}, {"species": [{"element": "O", "oxidation_state": -2.0, "occu": 1}], "abc": [0.626693806375026, 0.8640822227641837, 0.1337186176869129], "label": "O2-:1", "properties": {}}, {"species": [{"element": "O", "oxidation_state": -2.0, "occu": 1}], "abc": [0.8599944110670744, 0.6325353324215403, 0.1234290232638592], "label": "O2-:1", "properties": {}}, {"species": [{"element": "O", "oxidation_state": -2.0, "occu": 1}], "abc": [0.1343946594603211, 0.3844236150891526, 0.1359875345716229], "label": "O2-:1", "properties": {}}, {"species": [{"element": "O", "oxidation_state": -2.0, "occu": 1}], "abc": [0.3791914102132511, 0.1374229257120657, 0.1383215564125921], "label": "O2-:1", "properties": {}}, {"species": [{"element": "O", "oxidation_state": -2.0, "occu": 1}], "abc": [0.6332095467985374, 0.3836577949665256, 0.6322350279459794], "label": "O2-:1", "properties": {}}, {"species": [{"element": "O", "oxidation_state": -2.0, "occu": 1}], "abc": [0.8778151099389414, 0.1383942578479807, 0.6223911600735733], "label": "O2-:1", "properties": {}}]}