{"@module": "pymatgen.core.structure", "@class": "Structure", "charge": "null", "lattice": {"a": 8.51, "b": 8.51, "c": 8.51, "alpha": 90, "beta": 90, "gamma": 90}, "energy": -366.11345, "sites": [{"species": [{"element": "Mg", "oxidation_state": 2.0, "occu": 1}], "abc": [0.3774257266778386, 0.6246952077112117, 0.8745515157539977], "label": "Mg2+:1", "properties": {}}, {"species": [{"element": "Mg", "oxidation_state": 2.0, "occu": 1}], "abc": [0.8741189135690096, 0.1260654150903042, 0.8753392977863306], "label": "Mg2+:1", "properties": {}}, {"species": [{"element": "Mg", "oxidation_state": 2.0, "occu": 1}], "abc": [0.6253074724961595, 0.376862650896686, 0.8756058227765774], "label": "Mg2+:1", "properties": {}}, {"species": [{"element": "Mg", "oxidation_state": 2.0, "occu": 1}], "abc": [0.1252030660618506, 0.3753268503608157, 0.3748580993586452], "label": "Mg2+:1", "properties": {}}, {"species": [{"element": "Mg", "oxidation_state": 2.0, "occu": 1}], "abc": [0.8745729508422782, 0.6235614341975618, 0.3743653938854772], "label": "Mg2+:1", "properties": {}}, {"species": [{"element": "Mg", "oxidation_state": 2.0, "occu": 1}], "abc": [0.3753835078479225, 0.874771360885356, 0.6249605108478229], "label": "Mg2+:1", "properties": {}}, {"species": [{"element": "Mg", "oxidation_state": 2.0, "occu": 1}], "abc": [0.3747589687787224, 0.1256608535432405, 0.3758230339445184], "label": "Mg2+:1", "properties": {}}, {"species": [{"element": "Mg", "oxidation_state": 2.0, "occu": 1}], "abc": [0.625318015059985, 0.6239203716094824, 0.1233847667490063], "label": "Mg2+:1", "properties": {}}, {"species": [{"element": "Fe", "oxidation_state": 3.0, "occu": 1}], "abc": [0.6222376530488397, 0.8725558281079234, 0.3754623809886322], "label": "Fe3+:1", "properties": {}}, {"species": [{"element": "Fe", "oxidation_state": 3.0, "occu": 1}], "abc": [0.1278004585360293, 0.624214377100265, 0.6223895226277256], "label": "Fe3+:1", "properties": {}}, {"species": [{"element": "Fe", "oxidation_state": 3.0, "occu": 1}], "abc": [0.1272553908092924, 0.8751954427857725, 0.8738880452797123], "label": "Fe3+:1", "properties": {}}, {"species": [{"element": "Fe", "oxidation_state": 3.0, "occu": 1}], "abc": [0.8747284304485348, 0.3752831723060077, 0.6249350126664561], "label": "Fe3+:1", "properties": {}}, {"species": [{"element": "Fe", "oxidation_state": 3.0, "occu": 1}], "abc": [0.6220823263144595, 0.1252984341184619, 0.6272176863199768], "label": "Fe3+:1", "properties": {}}, {"species": [{"element": "Fe", "oxidation_state": 3.0, "occu": 1}], "abc": [0.8736839771088454, 0.8725667391356315, 0.1244918416312162], "label": "Fe3+:1", "properties": {}}, {"species": [{"element": "Fe", "oxidation_state": 3.0, "occu": 1}], "abc": [0.3778379264957621, 0.377179013508975, 0.1257635159233966], "label": "Fe3+:1", "properties": {}}, {"species": [{"element": "Fe", "oxidation_state": 3.0, "occu": 1}], "abc": [0.1247359222297927, 0.1270360687174348, 0.1270752069033545], "label": "Fe3+:1", "properties": {}}, {"species": [{"element": "Fe", "oxidation_state": 3.0, "occu": 1}], "abc": [0.2527344183520225, 0.7472761181545685, 0.2529010131384468], "label": "Fe3+:1", "properties": {}}, {"species": [{"element": "Fe", "oxidation_state": 3.0, "occu": 1}], "abc": [0.7501861408870425, 0.2491780648939855, 0.253713184247349], "label": "Fe3+:1", "properties": {}}, {"species": [{"element": "Fe", "oxidation_state": 3.0, "occu": 1}], "abc": [0.7507454131496218, 0.7473180583138922, 0.7528075526210288], "label": "Fe3+:1", "properties": {}}, {"species": [{"element": "Fe", "oxidation_state": 3.0, "occu": 1}], "abc": [0.2527770379561284, 0.250100935427754, 0.7537106376467955], "label": "Fe3+:1", "properties": {}}, {"species": [{"element": "Fe", "oxidation_state": 3.0, "occu": 1}], "abc": [-0.0022417015204818, 0.0014480131991716, 0.4968932870042057], "label": "Fe3+:1", "properties": {}}, {"species": [{"element": "Fe", "oxidation_state": 3.0, "occu": 1}], "abc": [0.4983016335595418, 0.50111599135939, 0.496749923224409], "label": "Fe3+:1", "properties": {}}, {"species": [{"element": "Fe", "oxidation_state": 3.0, "occu": 1}], "abc": [-0.0013268110511543, 0.5014682088434084, -0.0036721890383227], "label": "Fe3+:1", "properties": {}}, {"species": [{"element": "Fe", "oxidation_state": 3.0, "occu": 1}], "abc": [0.4980501642653564, 0.0017393386285887, -0.0027959362952397], "label": "Fe3+:1", "properties": {}}, {"species": [{"element": "O", "oxidation_state": -2.0, "occu": 1}], "abc": [0.1216899030079176, 0.1147611615385534, 0.8838145659309199], "label": "O2-:1", "properties": {}}, {"species": [{"element": "O", "oxidation_state": -2.0, "occu": 1}], "abc": [0.8787879782651187, 0.3785141003354101, 0.3859979379168714], "label": "O2-:1", "properties": {}}, {"species": [{"element": "O", "oxidation_state": -2.0, "occu": 1}], "abc": [0.3862484158830677, 0.8791944931411522, 0.3776712305599242], "label": "O2-:1", "properties": {}}, {"species": [{"element": "O", "oxidation_state": -2.0, "occu": 1}], "abc": [0.6202242122450994, 0.6221353053931493, 0.8788112929565731], "label": "O2-:1", "properties": {}}, {"species": [{"element": "O", "oxidation_state": -2.0, "occu": 1}], "abc": [0.3782685224517788, 0.3783555994925621, 0.8871033086833325], "label": "O2-:1", "properties": {}}, {"species": [{"element": "O", "oxidation_state": -2.0, "occu": 1}], "abc": [0.6223439828626454, 0.11454793396028, 0.3850143211355991], "label": "O2-:1", "properties": {}}, {"species": [{"element": "O", "oxidation_state": -2.0, "occu": 1}], "abc": [0.8720585136817605, 0.3707851000914695, 0.8639062258058549], "label": "O2-:1", "properties": {}}, {"species": [{"element": "O", "oxidation_state": -2.0, "occu": 1}], "abc": [0.1286427000647631, 0.1266632785560042, 0.363999968464343], "label": "O2-:1", "properties": {}}, {"species": [{"element": "O", "oxidation_state": -2.0, "occu": 1}], "abc": [0.6289382020574027, 0.6374984682332252, 0.3722663687153163], "label": "O2-:1", "properties": {}}, {"species": [{"element": "O", "oxidation_state": -2.0, "occu": 1}], "abc": [0.3626564719041021, 0.8717217849368666, 0.8723251359008766], "label": "O2-:1", "properties": {}}, {"species": [{"element": "O", "oxidation_state": -2.0, "occu": 1}], "abc": [0.1276166256609491, 0.6357675261997986, 0.8652807791850377], "label": "O2-:1", "properties": {}}, {"species": [{"element": "O", "oxidation_state": -2.0, "occu": 1}], "abc": [0.866332994670436, 0.8722459079967718, 0.364862899921469], "label": "O2-:1", "properties": {}}, {"species": [{"element": "O", "oxidation_state": -2.0, "occu": 1}], "abc": [0.6290348114265784, 0.1265993625675712, 0.8632847253004423], "label": "O2-:1", "properties": {}}, {"species": [{"element": "O", "oxidation_state": -2.0, "occu": 1}], "abc": [0.1207909401590714, 0.6232579955355968, 0.3868278746721624], "label": "O2-:1", "properties": {}}, {"species": [{"element": "O", "oxidation_state": -2.0, "occu": 1}], "abc": [0.8847482285351638, 0.8785758705006964, 0.8850065728440392], "label": "O2-:1", "properties": {}}, {"species": [{"element": "O", "oxidation_state": -2.0, "occu": 1}], "abc": [0.3709662375762756, 0.3709431940231643, 0.3634449105921095], "label": "O2-:1", "properties": {}}, {"species": [{"element": "O", "oxidation_state": -2.0, "occu": 1}], "abc": [0.3766846195852331, 0.6141290651545982, 0.1218646263355396], "label": "O2-:1", "properties": {}}, {"species": [{"element": "O", "oxidation_state": -2.0, "occu": 1}], "abc": [0.6169618779936071, 0.37546503614539, 0.1232362651340037], "label": "O2-:1", "properties": {}}, {"species": [{"element": "O", "oxidation_state": -2.0, "occu": 1}], "abc": [0.624906840211512, 0.8831500498094182, 0.6173889047645151], "label": "O2-:1", "properties": {}}, {"species": [{"element": "O", "oxidation_state": -2.0, "occu": 1}], "abc": [0.3848012332263361, 0.1228517942221836, 0.6217993814068361], "label": "O2-:1", "properties": {}}, {"species": [{"element": "O", "oxidation_state": -2.0, "occu": 1}], "abc": [0.1175329303908274, 0.3814417734198524, 0.6237996040901821], "label": "O2-:1", "properties": {}}, {"species": [{"element": "O", "oxidation_state": -2.0, "occu": 1}], "abc": [0.8844531974169569, 0.6160070318883867, 0.6223828169834205], "label": "O2-:1", "properties": {}}, {"species": [{"element": "O", "oxidation_state": -2.0, "occu": 1}], "abc": [0.8842402836361558, 0.1167332001703171, 0.1225314544052089], "label": "O2-:1", "properties": {}}, {"species": [{"element": "O", "oxidation_state": -2.0, "occu": 1}], "abc": [0.1185360696480829, 0.8814735919792369, 0.1191370870116938], "label": "O2-:1", "properties": {}}, {"species": [{"element": "O", "oxidation_state": -2.0, "occu": 1}], "abc": [0.1248365967355726, 0.8692201981092958, 0.6328522027650415], "label": "O2-:1", "properties": {}}, {"species": [{"element": "O", "oxidation_state": -2.0, "occu": 1}], "abc": [0.3632179298979121, 0.6272637669506902, 0.627841638609626], "label": "O2-:1", "properties": {}}, {"species": [{"element": "O", "oxidation_state": -2.0, "occu": 1}], "abc": [0.8737694027643635, 0.6358810881136396, 0.1283539525775503], "label": "O2-:1", "properties": {}}, {"species": [{"element": "O", "oxidation_state": -2.0, "occu": 1}], "abc": [0.6337452683061184, 0.8757365921952375, 0.1319786181072331], "label": "O2-:1", "properties": {}}, {"species": [{"element": "O", "oxidation_state": -2.0, "occu": 1}], "abc": [0.3649553080771655, 0.1328083497720879, 0.1274230319296388], "label": "O2-:1", "properties": {}}, {"species": [{"element": "O", "oxidation_state": -2.0, "occu": 1}], "abc": [0.1298162252733066, 0.366049209250533, 0.1261096383034044], "label": "O2-:1", "properties": {}}, {"species": [{"element": "O", "oxidation_state": -2.0, "occu": 1}], "abc": [0.6328683798200884, 0.3668140950950909, 0.6256578562915635], "label": "O2-:1", "properties": {}}, {"species": [{"element": "O", "oxidation_state": -2.0, "occu": 1}], "abc": [0.8676480946412314, 0.13357012632588, 0.6276056767081523], "label": "O2-:1", "properties": {}}]}