{"@module": "pymatgen.core.structure", "@class": "Structure", "charge": "null", "lattice": {"a": 8.43, "b": 8.43, "c": 8.43, "alpha": 90, "beta": 90, "gamma": 90}, "energy": -369.34091, "sites": [{"species": [{"element": "Mg", "oxidation_state": 2.0, "occu": 1}], "abc": [0.4952516490712263, 0.0027724952007213, -0.0016299534631242], "label": "Mg2+:1", "properties": {}}, {"species": [{"element": "Mg", "oxidation_state": 2.0, "occu": 1}], "abc": [0.2539694386782822, 0.7475589159084649, 0.2453660591023416], "label": "Mg2+:1", "properties": {}}, {"species": [{"element": "Mg", "oxidation_state": 2.0, "occu": 1}], "abc": [0.8752956783441055, 0.8746141572914805, 0.1226493228013198], "label": "Mg2+:1", "properties": {}}, {"species": [{"element": "Mg", "oxidation_state": 2.0, "occu": 1}], "abc": [0.3740609932829156, 0.8727991766266896, 0.6269140624968979], "label": "Mg2+:1", "properties": {}}, {"species": [{"element": "Mg", "oxidation_state": 2.0, "occu": 1}], "abc": [0.3744004769897418, 0.6243793741709946, 0.874293351577225], "label": "Mg2+:1", "properties": {}}, {"species": [{"element": "Mg", "oxidation_state": 2.0, "occu": 1}], "abc": [0.1251495664631097, 0.6254536004212331, 0.6253399790942203], "label": "Mg2+:1", "properties": {}}, {"species": [{"element": "Mg", "oxidation_state": 2.0, "occu": 1}], "abc": [0.8750551371031294, 0.3758655559038793, 0.6289706731294609], "label": "Mg2+:1", "properties": {}}, {"species": [{"element": "Mg", "oxidation_state": 2.0, "occu": 1}], "abc": [0.8736898864477965, 0.1255748468669268, 0.8740796581201775], "label": "Mg2+:1", "properties": {}}, {"species": [{"element": "Al", "oxidation_state": 3.0, "occu": 1}], "abc": [0.626107936677182, 0.3726286052325448, 0.8750885764690002], "label": "Al3+:1", "properties": {}}, {"species": [{"element": "Al", "oxidation_state": 3.0, "occu": 1}], "abc": [0.3760853427440768, 0.3757906161027446, 0.1217784589580782], "label": "Al3+:1", "properties": {}}, {"species": [{"element": "Fe", "oxidation_state": 3.0, "occu": 1}], "abc": [-0.0029939386902839, -0.000560351809663, 0.5032191086091482], "label": "Fe3+:1", "properties": {}}, {"species": [{"element": "Fe", "oxidation_state": 3.0, "occu": 1}], "abc": [0.4973681158263736, 0.4993798825996877, 0.5040355024624771], "label": "Fe3+:1", "properties": {}}, {"species": [{"element": "Fe", "oxidation_state": 3.0, "occu": 1}], "abc": [0.7517316242034876, 0.2515816476128915, 0.2455921168605523], "label": "Fe3+:1", "properties": {}}, {"species": [{"element": "Fe", "oxidation_state": 3.0, "occu": 1}], "abc": [0.7524799213553665, 0.7476284916231659, 0.7505617298329642], "label": "Fe3+:1", "properties": {}}, {"species": [{"element": "Fe", "oxidation_state": 3.0, "occu": 1}], "abc": [-0.0040592146931628, 0.4989038617189464, -0.000324155924747], "label": "Fe3+:1", "properties": {}}, {"species": [{"element": "Fe", "oxidation_state": 3.0, "occu": 1}], "abc": [0.2555266635871478, 0.2522478788047893, 0.7513086066395239], "label": "Fe3+:1", "properties": {}}, {"species": [{"element": "Fe", "oxidation_state": 3.0, "occu": 1}], "abc": [0.1276520651472059, 0.872213462185855, 0.8742709278017624], "label": "Fe3+:1", "properties": {}}, {"species": [{"element": "Fe", "oxidation_state": 3.0, "occu": 1}], "abc": [0.1252037149547958, 0.378281608067863, 0.3779115705509254], "label": "Fe3+:1", "properties": {}}, {"species": [{"element": "Fe", "oxidation_state": 3.0, "occu": 1}], "abc": [0.1246061246585405, 0.1236165997904372, 0.1220166310157706], "label": "Fe3+:1", "properties": {}}, {"species": [{"element": "Fe", "oxidation_state": 3.0, "occu": 1}], "abc": [0.627621662343858, 0.125844651707855, 0.6313936074620199], "label": "Fe3+:1", "properties": {}}, {"species": [{"element": "Fe", "oxidation_state": 3.0, "occu": 1}], "abc": [0.3752564511241752, 0.1237789569085448, 0.3744418840831366], "label": "Fe3+:1", "properties": {}}, {"species": [{"element": "Fe", "oxidation_state": 3.0, "occu": 1}], "abc": [0.8775478411802299, 0.6254274686179109, 0.377652151536115], "label": "Fe3+:1", "properties": {}}, {"species": [{"element": "Fe", "oxidation_state": 3.0, "occu": 1}], "abc": [0.623943272017535, 0.8746609142091275, 0.373986516916549], "label": "Fe3+:1", "properties": {}}, {"species": [{"element": "Fe", "oxidation_state": 3.0, "occu": 1}], "abc": [0.6220580543251948, 0.6260419692518085, 0.1217992205955479], "label": "Fe3+:1", "properties": {}}, {"species": [{"element": "O", "oxidation_state": -2.0, "occu": 1}], "abc": [0.1233380746795413, 0.1235547390551808, 0.882252800380369], "label": "O2-:1", "properties": {}}, {"species": [{"element": "O", "oxidation_state": -2.0, "occu": 1}], "abc": [0.882448763801419, 0.3815766251107354, 0.3765042263667865], "label": "O2-:1", "properties": {}}, {"species": [{"element": "O", "oxidation_state": -2.0, "occu": 1}], "abc": [0.3890635281663875, 0.890597720140854, 0.3806376395032608], "label": "O2-:1", "properties": {}}, {"species": [{"element": "O", "oxidation_state": -2.0, "occu": 1}], "abc": [0.62506955984604, 0.6056940791267695, 0.882720025689787], "label": "O2-:1", "properties": {}}, {"species": [{"element": "O", "oxidation_state": -2.0, "occu": 1}], "abc": [0.3924051836399858, 0.3744826727427926, 0.8918371448860357], "label": "O2-:1", "properties": {}}, {"species": [{"element": "O", "oxidation_state": -2.0, "occu": 1}], "abc": [0.6202195591288152, 0.1218492307773173, 0.3799742442907376], "label": "O2-:1", "properties": {}}, {"species": [{"element": "O", "oxidation_state": -2.0, "occu": 1}], "abc": [0.855552681271932, 0.3729811273668972, 0.8742394273730212], "label": "O2-:1", "properties": {}}, {"species": [{"element": "O", "oxidation_state": -2.0, "occu": 1}], "abc": [0.1315307250985225, 0.1325538356443182, 0.3692253582169305], "label": "O2-:1", "properties": {}}, {"species": [{"element": "O", "oxidation_state": -2.0, "occu": 1}], "abc": [0.6311453401034305, 0.6289773262695926, 0.369732160158144], "label": "O2-:1", "properties": {}}, {"species": [{"element": "O", "oxidation_state": -2.0, "occu": 1}], "abc": [0.3595510064790906, 0.8653583871815282, 0.867523682921065], "label": "O2-:1", "properties": {}}, {"species": [{"element": "O", "oxidation_state": -2.0, "occu": 1}], "abc": [0.1244456932200961, 0.6302898520109123, 0.8733616523048509], "label": "O2-:1", "properties": {}}, {"species": [{"element": "O", "oxidation_state": -2.0, "occu": 1}], "abc": [0.8663757380033413, 0.8660490225928227, 0.3721528850564745], "label": "O2-:1", "properties": {}}, {"species": [{"element": "O", "oxidation_state": -2.0, "occu": 1}], "abc": [0.6303453553354628, 0.1470429486313969, 0.8644651067245204], "label": "O2-:1", "properties": {}}, {"species": [{"element": "O", "oxidation_state": -2.0, "occu": 1}], "abc": [0.1120403260160102, 0.611618409498159, 0.3800309172731373], "label": "O2-:1", "properties": {}}, {"species": [{"element": "O", "oxidation_state": -2.0, "occu": 1}], "abc": [0.8825223282316194, 0.8786969390523316, 0.8777944684349335], "label": "O2-:1", "properties": {}}, {"species": [{"element": "O", "oxidation_state": -2.0, "occu": 1}], "abc": [0.3700187957132943, 0.3695151931951184, 0.3589802671487254], "label": "O2-:1", "properties": {}}, {"species": [{"element": "O", "oxidation_state": -2.0, "occu": 1}], "abc": [0.3890119008991147, 0.5979267996712595, 0.1201627603730666], "label": "O2-:1", "properties": {}}, {"species": [{"element": "O", "oxidation_state": -2.0, "occu": 1}], "abc": [0.6114548121925383, 0.3764246266480257, 0.1110186789574266], "label": "O2-:1", "properties": {}}, {"species": [{"element": "O", "oxidation_state": -2.0, "occu": 1}], "abc": [0.3854989856338291, 0.1267256328072096, 0.6140089219909904], "label": "O2-:1", "properties": {}}, {"species": [{"element": "O", "oxidation_state": -2.0, "occu": 1}], "abc": [0.6239438122431964, 0.88481973731772, 0.6185247310904914], "label": "O2-:1", "properties": {}}, {"species": [{"element": "O", "oxidation_state": -2.0, "occu": 1}], "abc": [0.8759675970570175, 0.6196514344532696, 0.6129862548554489], "label": "O2-:1", "properties": {}}, {"species": [{"element": "O", "oxidation_state": -2.0, "occu": 1}], "abc": [0.1235673235948771, 0.3747572136295879, 0.6153038266685352], "label": "O2-:1", "properties": {}}, {"species": [{"element": "O", "oxidation_state": -2.0, "occu": 1}], "abc": [0.8862700824669575, 0.1246356842404275, 0.1227993482901136], "label": "O2-:1", "properties": {}}, {"species": [{"element": "O", "oxidation_state": -2.0, "occu": 1}], "abc": [0.1189794086930309, 0.890974447638821, 0.1134166476879436], "label": "O2-:1", "properties": {}}, {"species": [{"element": "O", "oxidation_state": -2.0, "occu": 1}], "abc": [0.1266056346445435, 0.8737618065596763, 0.6330343172573918], "label": "O2-:1", "properties": {}}, {"species": [{"element": "O", "oxidation_state": -2.0, "occu": 1}], "abc": [0.3700620557487637, 0.6268184639993863, 0.6274813737099756], "label": "O2-:1", "properties": {}}, {"species": [{"element": "O", "oxidation_state": -2.0, "occu": 1}], "abc": [0.6301617441339366, 0.861189303531459, 0.137210783982396], "label": "O2-:1", "properties": {}}, {"species": [{"element": "O", "oxidation_state": -2.0, "occu": 1}], "abc": [0.864505492711599, 0.6238883375675198, 0.1363194448257349], "label": "O2-:1", "properties": {}}, {"species": [{"element": "O", "oxidation_state": -2.0, "occu": 1}], "abc": [0.141628701694542, 0.370696130314894, 0.1302072647976548], "label": "O2-:1", "properties": {}}, {"species": [{"element": "O", "oxidation_state": -2.0, "occu": 1}], "abc": [0.3650951842660815, 0.1500209337313737, 0.1373906162811537], "label": "O2-:1", "properties": {}}, {"species": [{"element": "O", "oxidation_state": -2.0, "occu": 1}], "abc": [0.6249640448102537, 0.3690911649471297, 0.6422141820282531], "label": "O2-:1", "properties": {}}, {"species": [{"element": "O", "oxidation_state": -2.0, "occu": 1}], "abc": [0.8632020973327005, 0.1312957895306144, 0.6257732337473021], "label": "O2-:1", "properties": {}}]}